README.rst
setup.py
nutella/model.py
nutella/version.py
nutella.egg-info/PKG-INFO
nutella.egg-info/SOURCES.txt
nutella.egg-info/dependency_links.txt
nutella.egg-info/requires.txt
nutella.egg-info/top_level.txt