Metadata-Version: 1.1
Name: nutella
Version: 0.0.0
Summary: great (point) spreads for Kepler, K2, and TESS
Home-page: https://github.com/benmontet/nutella
Author: Ben Montet and GitHub contributors
Author-email: bmontet@uchicago.edu
License: MIT
Keywords: astronomy statistics probability
Platform: UNKNOWN
Classifier: Development Status :: 3 - Alpha
Classifier: Intended Audience :: Science/Research
Classifier: License :: OSI Approved :: MIT License
Classifier: Programming Language :: Python :: 3.6
